spriteutilkhangvu/__init__.py
spriteutilkhangvu/spriteutil.py
spriteutilkhangvu-1.0.4.dist-info/LICENSE.md
spriteutilkhangvu-1.0.4.dist-info/METADATA
spriteutilkhangvu-1.0.4.dist-info/WHEEL
spriteutilkhangvu-1.0.4.dist-info/top_level.txt
spriteutilkhangvu-1.0.4.dist-info/RECORD
