Metadata-Version: 2.1
Name: spriteutilkhangvu
Version: 1.0.4
Summary: An internal project for Intek Institute
Home-page: https://github.com/khagkhangg/sprite_sheet_solution
Author: Khang VU
Author-email: khang.vu@alumni.intek.edu.vn
License: UNKNOWN
Platform: UNKNOWN
Classifier: Programming Language :: Python :: 3
Classifier: License :: OSI Approved :: MIT License
Classifier: Operating System :: OS Independent
Requires-Python: >=3.7
Requires-Dist: bleach
Requires-Dist: certifi
Requires-Dist: chardet
Requires-Dist: docutils
Requires-Dist: idna
Requires-Dist: numpy
Requires-Dist: pathlib
Requires-Dist: Pillow
Requires-Dist: pkginfo
Requires-Dist: Pygments
Requires-Dist: readme-renderer
Requires-Dist: requests
Requires-Dist: requests-toolbelt
Requires-Dist: six
Requires-Dist: tqdm
Requires-Dist: twine
Requires-Dist: urllib3
Requires-Dist: webencodings
